ankiazvox/__init__.py
ankiazvox/main.py
ankiazvox-0.6.0.dist-info/METADATA
ankiazvox-0.6.0.dist-info/WHEEL
ankiazvox-0.6.0.dist-info/entry_points.txt
ankiazvox-0.6.0.dist-info/licenses/LICENSE
ankiazvox-0.6.0.dist-info/RECORD
