Metadata-Version: 2.4
Name: ankiazvox
Version: 0.6.0
Summary: A CLI tool to synchronize Anki notes with high-quality Azure TTS audio.
License: MIT
License-File: LICENSE
Author: Eric Xu
Author-email: xulihua2006@gmail.com
Requires-Python: >=3.11,<4.0
Classifier: License :: OSI Approved :: MIT License
Classifier: Programming Language :: Python :: 3
Classifier: Programming Language :: Python :: 3.11
Classifier: Programming Language :: Python :: 3.12
Classifier: Programming Language :: Python :: 3.13
Classifier: Programming Language :: Python :: 3.14
Requires-Dist: azure-cognitiveservices-speech (>=1.47.0,<2.0.0)
Requires-Dist: beautifulsoup4 (>=4.14.3,<5.0.0)
Requires-Dist: click (>=8.3.1,<9.0.0)
Requires-Dist: python-dotenv (>=1.2.1,<2.0.0)
Requires-Dist: pyyaml (>=6.0.3,<7.0.0)
Requires-Dist: requests (>=2.32.5,<3.0.0)
Requires-Dist: tqdm (>=4.67.1,<5.0.0)
